python_logging_rabbitmq/__init__.py
python_logging_rabbitmq/compat.py
python_logging_rabbitmq/filters.py
python_logging_rabbitmq/formatters.py
python_logging_rabbitmq/handlers.py
python_logging_rabbitmq/handlers_oneway.py
python_logging_rabbitmq-2.3.0.dist-info/LICENSE.txt
python_logging_rabbitmq-2.3.0.dist-info/METADATA
python_logging_rabbitmq-2.3.0.dist-info/WHEEL
python_logging_rabbitmq-2.3.0.dist-info/top_level.txt
python_logging_rabbitmq-2.3.0.dist-info/zip-safe
python_logging_rabbitmq-2.3.0.dist-info/RECORD
