Metadata-Version: 2.1
Name: python-logging-rabbitmq
Version: 2.3.0
Summary: Send logs to RabbitMQ from Python/Django
Home-page: https://github.com/albertomr86/python-logging-rabbitmq
Author: Alberto Menendez Romero
Author-email: albertomr86@gmail.com
License: MIT
Keywords: logging rabbitmq logs
Classifier: Development Status :: 5 - Production/Stable
Classifier: Intended Audience :: Developers
Classifier: License :: OSI Approved :: MIT License
Classifier: Operating System :: OS Independent
Classifier: Programming Language :: Python
Classifier: Programming Language :: Python :: 2
Classifier: Programming Language :: Python :: 2.7
Classifier: Programming Language :: Python :: 3
Classifier: Programming Language :: Python :: 3.3
Classifier: Programming Language :: Python :: 3.4
Classifier: Programming Language :: Python :: 3.5
Classifier: Programming Language :: Python :: 3.6
Classifier: Programming Language :: Python :: 3.7
Classifier: Programming Language :: Python :: 3.8
Classifier: Programming Language :: Python :: 3.9
Requires-Python: >=2.7, !=3.0.*, !=3.1.*, !=3.2.*, !=3.3.*, !=3.4.*, !=3.5.*
License-File: LICENSE.txt
Requires-Dist: pika >=0.13
Provides-Extra: dev
Requires-Dist: check-manifest ; extra == 'dev'
